probablepeople/__init__.py
probablepeople/company_learned_settings.crfsuite
probablepeople/gender.py
probablepeople/generic_learned_settings.crfsuite
probablepeople/person_learned_settings.crfsuite
probablepeople/ratios.py
probablepeople-0.5.6.dist-info/LICENSE
probablepeople-0.5.6.dist-info/METADATA
probablepeople-0.5.6.dist-info/WHEEL
probablepeople-0.5.6.dist-info/top_level.txt
probablepeople-0.5.6.dist-info/RECORD
