Metadata-Version: 2.1
Name: probablepeople
Version: 0.5.6
Summary: Parse romanized names & companies using advanced NLP methods
License: MIT License
Project-URL: Homepage, https://github.com/datamade/probablepeople
Classifier: Development Status :: 3 - Alpha
Classifier: Intended Audience :: Developers
Classifier: Intended Audience :: Science/Research
Classifier: License :: OSI Approved :: MIT License
Classifier: Natural Language :: English
Classifier: Operating System :: MacOS :: MacOS X
Classifier: Operating System :: Microsoft :: Windows
Classifier: Operating System :: POSIX
Classifier: Topic :: Software Development :: Libraries :: Python Modules
Classifier: Topic :: Scientific/Engineering
Classifier: Topic :: Scientific/Engineering :: Information Analysis
Requires-Python: >=3.9
License-File: LICENSE
Requires-Dist: python-crfsuite>=0.7
Requires-Dist: probableparsing
Requires-Dist: doublemetaphone
Provides-Extra: dev
Requires-Dist: pytest; extra == "dev"
Requires-Dist: black; extra == "dev"
Requires-Dist: isort; extra == "dev"
Requires-Dist: mypy; extra == "dev"
Requires-Dist: flake8; extra == "dev"
Requires-Dist: parserator; extra == "dev"
Requires-Dist: pre-commit; extra == "dev"
